Workbook

Sheet Sheet1
A1: id | B1: dateExpiration | C1: category | D1: Type | E1: name | F1: dateCreation | G1: file
A2: 4519252 | C2: Resume | D2: =IFERROR(INDEX(Types!B:B, MATCH(C2,Types!A:A, 0)), "") -> CV | E2: resume.doc | F2: 2010-08-20 10:21:29 | G2: attachments/4459036.doc
A3: 4519263 | C3: Resume | D3: =IFERROR(INDEX(Types!B:B, MATCH(C3,Types!A:A, 0)), "") -> CV | E3: MigratedCV_1.doc | F3: 2007-09-15 19:05:29 | G3: attachments/4966312.doc
A4: 4519266 | C4: Resume | D4: =IFERROR(INDEX(Types!B:B, MATCH(C4,Types!A:A, 0)), "") -> CV | E4: Resume.Andrew Bailey. March 01. 2017.docx | F4: 2017-03-02 11:55:13 | G4: attachments/4459403.docx
A5: 4519266 | C5: License Document | D5: =IFERROR(INDEX(Types!B:B, MATCH(C5,Types!A:A, 0)), "") -> CoC | E5: updated firefighting.jpg | F5: 2017-03-02 11:55:12 | G5: attachments/4459402.jpg
A6: 4519266 | C6: Other Resume | D6: =IFERROR(INDEX(Types!B:B, MATCH(C6,Types!A:A, 0)), "") -> Other | E6: Resume,Andrew Bailey. May 2016.doc | F6: 2016-05-25 07:26:53 | G6: attachments/4459401.doc
A7: 4519266 | C7: License Document | D7: =IFERROR(INDEX(Types!B:B, MATCH(C7,Types!A:A, 0)), "") -> CoC | E7: ENG 1 Malta.jpg | F7: 2014-04-28 08:31:28 | G7: attachments/4459400.jpg
A8: 4519266 | C8: Verified Documents | D8: =IFERROR(INDEX(Types!B:B, MATCH(C8,Types!A:A, 0)), "") -> Verified Licences | E8: B1B2 copy.jpg | F8: 2014-04-28 08:30:47 | G8: attachments/4459399.jpg
A9: 4519266 | C9: Other Resume | D9: =IFERROR(INDEX(Types!B:B, MATCH(C9,Types!A:A, 0)), "") -> Other | E9: Resume,Andrew Bailey. Compressed version, 4 8 2014.doc | F9: 2014-04-24 09:35:48 | G9: attachments/4459398.doc
A10: 4519266 | C10: Other Resume | D10: =IFERROR(INDEX(Types!B:B, MATCH(C10,Types!A:A, 0)), "") -> Other | E10: Resume,Andrew Bailey. Compressed version, 4 9 2012.doc | F10: 2013-05-20 09:38:55 | G10: attachments/4459397.doc
A11: 4519266 | C11: Other Resume | D11: =IFERROR(INDEX(Types!B:B, MATCH(C11,Types!A:A, 0)), "") -> Other | E11: Resume,Andrew Bailey. Compressed version, 4 9 2012.doc | F11: 2012-05-01 09:45:32 | G11: attachments/4459396.doc
A12: 4519266 | C12: References | D12: =IFERROR(INDEX(Types!B:B, MATCH(C12,Types!A:A, 0)), "") -> Reference | E12: Spirit Ref Dale.jpg | F12: 2012-04-10 10:31:15 | G12: attachments/4459395.jpg
A13: 4519266 | C13: File | D13: =IFERROR(INDEX(Types!B:B, MATCH(C13,Types!A:A, 0)), "") -> Other | E13: Reference List for Andrew Bailey.docx | F13: 2012-04-10 07:28:49 | G13: attachments/4459370.docx
... A48: 4519376 | C48: Reference | D48: =IFERROR(INDEX(Types!B:B, MATCH(C48,Types!A:A, 0)), "") -> Reference | E48: Reference from Owners of Motor Yacht Domani.docx | F48: 2021-04-16 20:44:38 | G48: attachments/15223789.docx
A49: 4519376 | B49: 2022-05-09 00:00:00 | C49: Deck License | D49: =IFERROR(INDEX(Types!B:B, MATCH(C49,Types!A:A, 0)), "") -> CoC | E49: CoC. all pages. Peter Pexton.pdf | F49: 2021-04-16 20:44:37 | G49: attachments/15223787.pdf
A50: 4519376 | C50: Resume | D50: =IFERROR(INDEX(Types!B:B, MATCH(C50,Types!A:A, 0)), "") -> CV | E50: CAPTAIN_PETER_PEXTON_CV.pdf | F50: 2021-04-16 20:39:37 | G50: attachments/15223761.pdf
A51: 4519376 | C51: Resume | D51: =IFERROR(INDEX(Types!B:B, MATCH(C51,Types!A:A, 0)), "") -> CV | E51: CAPTAIN_PETER_PEXTON_CV.pdf | F51: 2021-04-15 23:02:51 | G51: attachments/15215697.pdf
A52: 4519376 | C52: Resume | D52: =IFERROR(INDEX(Types!B:B, MATCH(C52,Types!A:A, 0)), "") -> CV | E52: MigratedCV_1.doc | F52: 2007-09-15 19:03:02 | G52: attachments/4462811.doc
A53: 4519389 | C53: Resume | D53: =IFERROR(INDEX(Types!B:B, MATCH(C53,Types!A:A, 0)), "") -> CV | E53: PUCCI CAPTAINwpic.docx | F53: 2018-07-25 18:43:10 | G53: attachments/4463056.docx
A54: 4519389 | C54: Other Resume | D54: =IFERROR(INDEX(Types!B:B, MATCH(C54,Types!A:A, 0)), "") -> Other | E54: puccicaptainres15.docx | F54: 2018-07-25 18:41:07 | G54: attachments/4463055.docx
A55: 4519389 | C55: Other Resume | D55: =IFERROR(INDEX(Types!B:B, MATCH(C55,Types!A:A, 0)), "") -> Other | E55: lpucciNAresumed3.23.docx | F55: 2018-04-03 12:25:46 | G55: attachments/4463054.docx
A56: 4519389 | C56: Other Resume | D56: =IFERROR(INDEX(Types!B:B, MATCH(C56,Types!A:A, 0)), "") -> Other | E56: lpucciNAresumed3.23.docx | F56: 2018-03-27 17:40:27 | G56: attachments/4463053.docx
A57: 4519389 | C57: Other Resume | D57: =IFERROR(INDEX(Types!B:B, MATCH(C57,Types!A:A, 0)), "") -> Other | E57: PUCCI CAPTAINwpic.docx | F57: 2018-03-25 06:08:41 | G57: attachments/4463052.docx
A58: 4519389 | C58: Other Resume | D58: =IFERROR(INDEX(Types!B:B, MATCH(C58,Types!A:A, 0)), "") -> Other | E58: PUCCICAPTAINRES2.18.docx | F58: 2018-03-14 05:37:53 | G58: attachments/4463051.docx
A59: 4519389 | C59: CoverLetter | D59: =IFERROR(INDEX(Types!B:B, MATCH(C59,Types!A:A, 0)), "") -> Other / Unique | E59: USCG License reduced.pdf | F59: 2018-03-04 10:37:02 | G59: attachments/4463050.pdf
A60: 4519389 | C60: Other Resume | D60: =IFERROR(INDEX(Types!B:B, MATCH(C60,Types!A:A, 0)), "") -> Other | E60: PUCCICAPTAINRES2.18.docx | F60: 2018-03-04 10:32:41 | G60: attachments/4463049.docx
A61: 4519389 | C61: Other Resume | D61: =IFERROR(INDEX(Types!B:B, MATCH(C61,Types!A:A, 0)), "") -> Other | E61: PUCCICAPTAINRES10.17.doc | F61: 2017-11-10 14:27:09 | G61: attachments/4463048.doc
... A555: 4520175 | C555: Reference | D555: =IFERROR(INDEX(Types!B:B, MATCH(C555,Types!A:A, 0)), "") -> Reference | E555: Zanzibar_Murphy reference letter.docx | F555: 2019-07-23 13:08:10 | G555: attachments/5683540.docx
A556: 4520175 | B556: 2021-05-08 00:00:00 | C556: Marine Medical Certificate / ENG1 | D556: =IFERROR(INDEX(Types!B:B, MATCH(C556,Types!A:A, 0)), "") -> Medical | E556: USCG Medical Certificate.pdf | F556: 2019-05-14 13:52:33 | G556: attachments/5228646.pdf
A557: 4520175 | B557: 2025-02-03 00:00:00 | C557: Deck License | D557: =IFERROR(INDEX(Types!B:B, MATCH(C557,Types!A:A, 0)), "") -> CoC | E557: License_STCW_Medical_TWIC.pdf | F557: 2019-02-25 09:01:54 | G557: attachments/4488935.pdf
A558: 4520175 | C558: Resume | D558: =IFERROR(INDEX(Types!B:B, MATCH(C558,Types!A:A, 0)), "") -> CV | E558: Michael Murphy Resume Jan 2019.pdf | F558: 2019-02-22 15:36:59 | G558: attachments/4488934.pdf
A559: 4520175 | C559: Reference | D559: =IFERROR(INDEX(Types!B:B, MATCH(C559,Types!A:A, 0)), "") -> Reference | E559: Legendary Capt Michael Murphy letter of recommenda.pdf | F559: 2019-02-22 15:36:44 | G559: attachments/4488933.pdf
A560: 4520175 | C560: Other Resume | D560: =IFERROR(INDEX(Types!B:B, MATCH(C560,Types!A:A, 0)), "") -> Other | E560: Michael Murphy Resume 2016 Ft Lauderdale.docx | F560: 2017-08-23 08:59:33 | G560: attachments/4488932.docx
A561: 4520175 | C561: Other Resume | D561: =IFERROR(INDEX(Types!B:B, MATCH(C561,Types!A:A, 0)), "") -> Other | E561: Michael Murphy Resume 2 pg Feb 2015.pdf | F561: 2015-02-12 08:53:32 | G561: attachments/4488836.pdf
A562: 4520175 | C562: CoverLetter | D562: =IFERROR(INDEX(Types!B:B, MATCH(C562,Types!A:A, 0)), "") -> Other / Unique | E562: Signed Cover Letter.pdf | F562: 2015-02-12 08:53:32 | G562: attachments/4488835.pdf
A563: 4520175 | C563: Marine Medical Certificate / ENG1 | D563: =IFERROR(INDEX(Types!B:B, MATCH(C563,Types!A:A, 0)), "") -> Medical | E563: MMC Medical Evaluation.pdf | F563: 2014-08-18 15:37:06 | G563: attachments/4488734.pdf
A564: 4520175 | C564: References | D564: =IFERROR(INDEX(Types!B:B, MATCH(C564,Types!A:A, 0)), "") -> Reference | E564: Crew verbal reference April 29th 2014.docx | F564: 2014-04-29 10:29:36 | G564: attachments/4488732.docx
A565: 4520175 | C565: Other Resume | D565: =IFERROR(INDEX(Types!B:B, MATCH(C565,Types!A:A, 0)), "") -> Other | E565: Murphy-Michael 2014.docx | F565: 2014-03-21 07:55:41 | G565: attachments/4488731.docx
A566: 4520175 | C566: Other Resume | D566: =IFERROR(INDEX(Types!B:B, MATCH(C566,Types!A:A, 0)), "") -> Other | E566: Murphy-Michael_pic2(2)_try.pdf | F566: 2013-09-04 10:40:19 | G566: attachments/4488730.pdf
A567: 4520175 | C567: File | D567: =IFERROR(INDEX(Types!B:B, MATCH(C567,Types!A:A, 0)), "") -> Other | E567: Additional information.doc | F567: 2013-08-14 12:52:28 | G567: attachments/4488706.doc
A568: 4520175 | C568: File | D568: =IFERROR(INDEX(Types!B:B, MATCH(C568,Types!A:A, 0)), "") -> Other | E568: Photo.jpg | F568: 2013-07-29 08:53:32 | G568: attachments/4488705.jpg
A569: 4520175 | C569: Deck License | D569: =IFERROR(INDEX(Types!B:B, MATCH(C569,Types!A:A, 0)), "") -> CoC | E569: USCG Pg 3.pdf | F569: 2013-07-22 08:18:33 | G569: attachments/4488704.pdf
... A950: 4520687 | C950: Courses / Modules / Certificates | D950: =IFERROR(INDEX(Types!B:B, MATCH(C950,Types!A:A, 0)), "") -> Certificates | E950: ECDIS.pdf | F950: 2024-11-25 14:27:01 | G950: attachments/25996766.pdf
A951: 4520687 | C951: Marine Medical Certificate / ENG1 | D951: =IFERROR(INDEX(Types!B:B, MATCH(C951,Types!A:A, 0)), "") -> Medical | E951: Richard Lington ENG1 exp 26.04.26.pdf | F951: 2024-11-25 14:24:52
A952: 4520687 | C952: Courses / Modules / Certificates | D952: =IFERROR(INDEX(Types!B:B, MATCH(C952,Types!A:A, 0)), "") -> Certificates | E952: GMDSS_Coc_..JPG | F952: 2024-11-25 14:23:27
A953: 4520687 | C953: Other | D953: =IFERROR(INDEX(Types!B:B, MATCH(C953,Types!A:A, 0)), "") -> Other | E953: Captain Richard Lington CV OCT 2024.pdf | F953: 2024-11-25 14:22:44 | G953: attachments/25996703.pdf
A954: 4520687 | C954: Reference | D954: =IFERROR(INDEX(Types!B:B, MATCH(C954,Types!A:A, 0)), "") -> Reference | E954: Captain Richard Lington - reference letter.pdf | F954: 2024-11-25 14:22:29 | G954: attachments/25996695.pdf
A955: 4520687 | C955: Resume | D955: =IFERROR(INDEX(Types!B:B, MATCH(C955,Types!A:A, 0)), "") -> CV | E955: Captain Richard Lington CV OCT 2024.docx | F955: 2024-11-25 09:50:59 | G955: attachments/25993554.docx
A956: 4520687 | C956: Resume | D956: =IFERROR(INDEX(Types!B:B, MATCH(C956,Types!A:A, 0)), "") -> CV | E956: Captain Richard Lington CV March 2024.docx | F956: 2024-04-15 10:30:19 | G956: attachments/24282411.docx
A957: 4520687 | C957: Resume | D957: =IFERROR(INDEX(Types!B:B, MATCH(C957,Types!A:A, 0)), "") -> CV | E957: resume.doc | F957: 2010-08-20 10:20:07 | G957: attachments/4462875.doc
A958: 4520723 | C958: Resume | D958: =IFERROR(INDEX(Types!B:B, MATCH(C958,Types!A:A, 0)), "") -> CV | E958: resume.doc | F958: 2010-08-20 10:20:07 | G958: attachments/4463657.doc
A959: 4520726 | C959: Resume | D959: =IFERROR(INDEX(Types!B:B, MATCH(C959,Types!A:A, 0)), "") -> CV | E959: resume.doc | F959: 2010-08-20 10:20:07 | G959: attachments/4463734.doc
A960: 4520732 | C960: Resume | D960: =IFERROR(INDEX(Types!B:B, MATCH(C960,Types!A:A, 0)), "") -> CV | E960: PamelaGreenshieldscv-12re.doc | F960: 2012-10-31 11:59:57 | G960: attachments/4463979.doc
A961: 4520732 | C961: Other Resume | D961: =IFERROR(INDEX(Types!B:B, MATCH(C961,Types!A:A, 0)), "") -> Other | E961: PamelaGreenshieldscv-12re.doc | F961: 2012-10-22 07:59:51 | G961: attachments/4463978.doc
A962: 4520732 | C962: Other Resume | D962: =IFERROR(INDEX(Types!B:B, MATCH(C962,Types!A:A, 0)), "") -> Other | E962: PamelaGreenshieldscv-12re.doc | F962: 2012-10-15 05:20:51 | G962: attachments/4463977.doc
A963: 4520732 | C963: Other Resume | D963: =IFERROR(INDEX(Types!B:B, MATCH(C963,Types!A:A, 0)), "") -> Other | E963: PamelaGreenshieldscv-12re.doc | F963: 2012-10-02 04:19:05 | G963: attachments/4463976.doc
A964: 4520732 | C964: Other Resume | D964: =IFERROR(INDEX(Types!B:B, MATCH(C964,Types!A:A, 0)), "") -> Other | E964: PamelaGreenshieldscv-12.doc | F964: 2012-09-30 07:00:14 | G964: attachments/4463975.doc
... A1003: 4521438 | C1003: Other Resume | D1003: =IFERROR(INDEX(Types!B:B, MATCH(C1003,Types!A:A, 0)), "") -> Other | E1003: CV Navigation 2012.doc | F1003: 2012-05-23 10:08:07 | G1003: attachments/4484107.doc
A1004: 4521438 | C1004: File | D1004: =IFERROR(INDEX(Types!B:B, MATCH(C1004,Types!A:A, 0)), "") -> Other | E1004: Resumé Rémi Turcat-Sailing 2011.doc | F1004: 2011-08-01 08:54:54
A1005: 4521438 | C1005: File | D1005: =IFERROR(INDEX(Types!B:B, MATCH(C1005,Types!A:A, 0)), "") -> Other | E1005: CV Navigation 2011.doc | F1005: 2011-08-01 08:54:53
A1006: 4521440 | C1006: Resume | D1006: =IFERROR(INDEX(Types!B:B, MATCH(C1006,Types!A:A, 0)), "") -> CV | E1006: Document - Email Body.txt | F1006: 2019-01-23 18:43:43 | G1006: attachments/4484251.txt
A1007: 4521440 | C1007: Other Resume | D1007: =IFERROR(INDEX(Types!B:B, MATCH(C1007,Types!A:A, 0)), "") -> Other | E1007: CVSP_Capt Bill Hawes.doc | F1007: 2015-02-20 11:21:58 | G1007: attachments/4484248.doc
A1008: 4521440 | C1008: Other Resume | D1008: =IFERROR(INDEX(Types!B:B, MATCH(C1008,Types!A:A, 0)), "") -> Other | E1008: CVSP_Capt Bill Hawes.doc | F1008: 2015-02-20 08:24:46 | G1008: attachments/4484250.doc
A1009: 4521440 | C1009: Other Resume | D1009: =IFERROR(INDEX(Types!B:B, MATCH(C1009,Types!A:A, 0)), "") -> Other | E1009: CVSP_Capt Bill Hawes.doc | F1009: 2015-02-20 08:24:45 | G1009: attachments/4484249.doc
A1010: 4521443 | C1010: Deck License | D1010: =IFERROR(INDEX(Types!B:B, MATCH(C1010,Types!A:A, 0)), "") -> CoC | E1010: license.jpg | F1010: 2024-04-11 11:18:44 | G1010: attachments/24258282.jpg
A1011: 4521443 | C1011: Deck License | D1011: =IFERROR(INDEX(Types!B:B, MATCH(C1011,Types!A:A, 0)), "") -> CoC | E1011: license 2.jpg | F1011: 2024-04-11 11:18:43 | G1011: attachments/24258281.jpg
A1012: 4521443 | C1012: Deck License | D1012: =IFERROR(INDEX(Types!B:B, MATCH(C1012,Types!A:A, 0)), "") -> CoC | E1012: license 3.jpg | F1012: 2024-04-11 11:18:43 | G1012: attachments/24258280.jpg
A1013: 4521443 | C1013: TWIC Card - US | D1013: =IFERROR(INDEX(Types!B:B, MATCH(C1013,Types!A:A, 0)), "") -> Passport | E1013: TWIC card.jpg | F1013: 2024-04-11 11:18:43 | G1013: attachments/24258279.jpg
A1014: 4521443 | C1014: Marine Medical Certificate / ENG1 | D1014: =IFERROR(INDEX(Types!B:B, MATCH(C1014,Types!A:A, 0)), "") -> Medical | E1014: uscg medical.jpg | F1014: 2024-04-11 11:18:43 | G1014: attachments/24258278.jpg
A1015: 4521443 | C1015: Covid 19 test/vaccination | D1015: =IFERROR(INDEX(Types!B:B, MATCH(C1015,Types!A:A, 0)), "") -> Other | E1015: covid vaccination.jpg | F1015: 2024-04-11 11:18:42 | G1015: attachments/24258276.jpg
A1016: 4521443 | C1016: Courses / Modules / Certificates | D1016: =IFERROR(INDEX(Types!B:B, MATCH(C1016,Types!A:A, 0)), "") -> Certificates | E1016: emergency medical technician.jpg | F1016: 2024-04-11 11:18:42 | G1016: attachments/24258277.jpg
A1017: 4521443 | C1017: Reference | D1017: =IFERROR(INDEX(Types!B:B, MATCH(C1017,Types!A:A, 0)), "") -> Reference | E1017: reference-andiamo-erin.jpg | F1017: 2024-04-10 13:30:03 | G1017: attachments/24250227.jpg
... A1091: 4521077 | C1091: Resume | D1091: =IFERROR(INDEX(Types!B:B, MATCH(C1091,Types!A:A, 0)), "") -> CV | E1091: Wayne Torrance CV 2019.pdf | F1091: 2019-05-15 16:51:08 | G1091: attachments/5233945.pdf
A1092: 4521077 | B1092: 2023-05-09 00:00:00 | C1092: License | D1092: =IFERROR(INDEX(Types!B:B, MATCH(C1092,Types!A:A, 0)), "") -> CoC | E1092: Master Yachts 3000.pdf | F1092: 2019-05-03 19:00:06 | G1092: attachments/5167839.pdf
A1093: 4521077 | C1093: Other | D1093: =IFERROR(INDEX(Types!B:B, MATCH(C1093,Types!A:A, 0)), "") -> Other | E1093: GMDSS.pdf | F1093: 2019-05-03 19:00:05 | G1093: attachments/5167838.pdf
A1094: 4521077 | C1094: Resume | D1094: =IFERROR(INDEX(Types!B:B, MATCH(C1094,Types!A:A, 0)), "") -> CV | E1094: Wayne Torrance CV 2019.pdf | F1094: 2019-05-03 19:00:05 | G1094: attachments/5167837.pdf
A1095: 4521077 | B1095: 2022-01-10 00:00:00 | C1095: Other | D1095: =IFERROR(INDEX(Types!B:B, MATCH(C1095,Types!A:A, 0)), "") -> Other | E1095: STCW Basic Safety - exp 10 Jan 2022pdf.pdf | F1095: 2019-05-03 18:59:56 | G1095: attachments/5167836.pdf
A1096: 4521077 | B1096: 2022-01-11 00:00:00 | C1096: Other | D1096: =IFERROR(INDEX(Types!B:B, MATCH(C1096,Types!A:A, 0)), "") -> Other | E1096: STCW Advanced Fire Fighting - exp 11 Jan 2022.pdf | F1096: 2019-05-03 18:59:55 | G1096: attachments/5167834.pdf
A1097: 4521077 | B1097: 2022-01-12 00:00:00 | C1097: Other | D1097: =IFERROR(INDEX(Types!B:B, MATCH(C1097,Types!A:A, 0)), "") -> Other | E1097: STCW Survival Craft & rescue Boat - exp 12 Jan 2022.pdf | F1097: 2019-05-03 18:59:55 | G1097: attachments/5167835.pdf
A1098: 4521077 | C1098: Other | D1098: =IFERROR(INDEX(Types!B:B, MATCH(C1098,Types!A:A, 0)), "") -> Other | E1098: Medical care Aboard Ship - 2016.pdf | F1098: 2019-05-03 18:59:54 | G1098: attachments/5167832.pdf
A1099: 4521077 | C1099: Other | D1099: =IFERROR(INDEX(Types!B:B, MATCH(C1099,Types!A:A, 0)), "") -> Other | E1099: Medical first Aid - 2016.pdf | F1099: 2019-05-03 18:59:54 | G1099: attachments/5167833.pdf
A1100: 4521077 | C1100: Other | D1100: =IFERROR(INDEX(Types!B:B, MATCH(C1100,Types!A:A, 0)), "") -> Other | E1100: Leadership Course - 2013.pdf | F1100: 2019-05-03 18:59:50 | G1100: attachments/5167831.pdf
A1101: 4521077 | C1101: Other | D1101: =IFERROR(INDEX(Types!B:B, MATCH(C1101,Types!A:A, 0)), "") -> Other | E1101: Masters HELM - 2014.pdf | F1101: 2019-05-03 18:59:50 | G1101: attachments/5167830.pdf
A1102: 4521077 | C1102: Other | D1102: =IFERROR(INDEX(Types!B:B, MATCH(C1102,Types!A:A, 0)), "") -> Other | E1102: ECDIS - 2017.pdf | F1102: 2019-05-03 18:59:49 | G1102: attachments/5167828.pdf
A1103: 4521077 | C1103: Other | D1103: =IFERROR(INDEX(Types!B:B, MATCH(C1103,Types!A:A, 0)), "") -> Other | E1103: Ship Security Officer - 2014.pdf | F1103: 2019-05-03 18:59:49 | G1103: attachments/5167829.pdf
A1104: 4521077 | C1104: Other | D1104: =IFERROR(INDEX(Types!B:B, MATCH(C1104,Types!A:A, 0)), "") -> Other | E1104: ISM Safety Officer - 2013.pdf | F1104: 2019-05-03 18:59:48 | G1104: attachments/5167827.pdf
A1105: 4521077 | C1105: Other | D1105: =IFERROR(INDEX(Types!B:B, MATCH(C1105,Types!A:A, 0)), "") -> Other | E1105: PWC Certificate.pdf | F1105: 2019-05-03 18:59:38 | G1105: attachments/5167826.pdf
A1106: 4521077 | C1106: Resume | D1106: =IFERROR(INDEX(Types!B:B, MATCH(C1106,Types!A:A, 0)), "") -> CV | E1106: Wayne Torrance CV 2019.pdf | F1106: 2019-04-25 13:14:08 | G1106: attachments/5126373.pdf
A1107: 4521077 | C1107: Resume | D1107: =IFERROR(INDEX(Types!B:B, MATCH(C1107,Types!A:A, 0)), "") -> CV | E1107: Wayne Torrance CV 2019.pdf | F1107: 2019-04-25 11:11:28 | G1107: attachments/5125804.pdf
A1108: 4521077 | C1108: Cover Letter | D1108: =IFERROR(INDEX(Types!B:B, MATCH(C1108,Types!A:A, 0)), "") -> Other / Unique | E1108: Cover note.txt | F1108: 2019-04-18 13:26:07 | G1108: attachments/5111799.txt
A1109: 4521077 | C1109: Resume | D1109: =IFERROR(INDEX(Types!B:B, MATCH(C1109,Types!A:A, 0)), "") -> CV | E1109: Wayne Torrance CV 2019.pdf | F1109: 2019-04-18 13:26:05 | G1109: attachments/5111797.pdf
... A1228: 4521136 | C1228: Other Resume | D1228: =IFERROR(INDEX(Types!B:B, MATCH(C1228,Types!A:A, 0)), "") -> Other | E1228: CVSept2011.doc | F1228: 2011-10-19 09:19:04 | G1228: attachments/4475245.doc
A1229: 4521153 | B1229: 2027-04-03 00:00:00 | C1229: Other License/Degree | D1229: =IFERROR(INDEX(Types!B:B, MATCH(C1229,Types!A:A, 0)), "") -> Certificates | E1229: coc-loki.jpg | F1229: 2024-02-07 10:15:18 | G1229: attachments/23722645.jpg
A1230: 4521153 | C1230: Cover Letter | D1230: =IFERROR(INDEX(Types!B:B, MATCH(C1230,Types!A:A, 0)), "") -> Other / Unique | E1230: Cover note.txt | F1230: 2024-02-06 16:36:05 | G1230: attachments/23717006.txt
A1231: 4521153 | C1231: Resume | D1231: =IFERROR(INDEX(Types!B:B, MATCH(C1231,Types!A:A, 0)), "") -> CV | E1231: Lachlan Haig Resume 1-2024.docx | F1231: 2024-02-06 16:36:03 | G1231: attachments/23717000.docx
A1232: 4521153 | C1232: Cover Letter | D1232: =IFERROR(INDEX(Types!B:B, MATCH(C1232,Types!A:A, 0)), "") -> Other / Unique | E1232: Cover note.txt | F1232: 2024-02-05 15:38:26 | G1232: attachments/23702975.txt
A1233: 4521153 | C1233: Resume | D1233: =IFERROR(INDEX(Types!B:B, MATCH(C1233,Types!A:A, 0)), "") -> CV | E1233: Lachlan Haig Resume 1-2024.docx | F1233: 2024-02-05 15:38:25 | G1233: attachments/23702974.docx
A1234: 4521153 | C1234: Resume | D1234: =IFERROR(INDEX(Types!B:B, MATCH(C1234,Types!A:A, 0)), "") -> CV | E1234: resume.doc | F1234: 2010-08-20 10:20:08 | G1234: attachments/4475834.doc
A1235: 4521154 | C1235: Resume | D1235: =IFERROR(INDEX(Types!B:B, MATCH(C1235,Types!A:A, 0)), "") -> CV | E1235: David Fisher CV.docx | F1235: 2016-07-25 06:29:32 | G1235: attachments/4475912.docx
A1236: 4521154 | C1236: Other Resume | D1236: =IFERROR(INDEX(Types!B:B, MATCH(C1236,Types!A:A, 0)), "") -> Other | E1236: MigratedCV_1.doc | F1236: 2007-09-15 19:13:25 | G1236: attachments/4475911.doc
...

Sheet Types
A1: Category | B1: Type
A2: Resume | B2: CV
A3: STCW | B3: STCW
A4: Marine Medical Certificate / ENG1 | B4: Medical
A5: Medical Certificate | B5: Medical
A6: Passport | B6: Passport
A7: EU Residence Permit | B7: Passport
A8: Visa | B8: Passport
A9: Visa B1B2 | B9: Passport
A10: TWIC Card - US | B10: Passport
A11: B1/B2 visa | B11: Passport
A12: Visa | B12: Passport
... A42: Proposal View Data | B42: ???
